{
  "generated_at": "2026-06-24T04:04:15.170873+00:00",
  "window_days": 30,
  "primary_horizon": 5,
  "total_tracked": 13,
  "untracked_count": 0,
  "by_horizon": {
    "3d": {
      "evaluated": 11,
      "hit_rate": 0.545,
      "avg_return_pct": 1.07
    },
    "5d": {
      "evaluated": 5,
      "hit_rate": 0.2,
      "avg_return_pct": -8.96
    },
    "10d": {
      "evaluated": 0,
      "hit_rate": null,
      "avg_return_pct": null
    }
  },
  "by_direction": {
    "long": {
      "3d": {
        "evaluated": 8,
        "hit_rate": 0.5,
        "avg_return_pct": 2.02
      },
      "5d": {
        "evaluated": 4,
        "hit_rate": 0.25,
        "avg_return_pct": -9.92
      },
      "10d": {
        "evaluated": 0,
        "hit_rate": null,
        "avg_return_pct": null
      }
    },
    "short": {
      "3d": {
        "evaluated": 3,
        "hit_rate": 0.667,
        "avg_return_pct": -1.45
      },
      "5d": {
        "evaluated": 1,
        "hit_rate": 0.0,
        "avg_return_pct": -5.11
      },
      "10d": {
        "evaluated": 0,
        "hit_rate": null,
        "avg_return_pct": null
      }
    }
  }
}