{
  "generated_at": "2026-06-19T18:07:41.977395-04:00",
  "ticker_news": {
    "INTC": [
      {
        "id": "5be0992113131c09",
        "source": "alpaca",
        "publisher": "benzinga",
        "ticker": "INTC",
        "scope": "ticker",
        "title": "If You Invested $100 In Intel Stock 10 Years Ago, You Would Have This Much Today",
        "url": "https://www.benzinga.com/news/26/06/60002693/if-you-invested-100-intel-stock-10-years-ago-you-would-have-much-today",
        "published_at": "2026-06-19T20:45:37+00:00",
        "type": "other",
        "impact": "low",
        "dedup_group": "intc_historical_return_retrospective",
        "tickers_mentioned": [],
        "route_to_synthesis": false
      }
    ]
  },
  "macro_events": []
}