{
  "generated_at": "2026-05-11T18:45:25.420728-04:00",
  "ticker_news": {
    "ISRG": [
      {
        "id": "12da4ee2f86ef9ff",
        "source": "alpaca",
        "publisher": "benzinga",
        "ticker": "ISRG",
        "scope": "ticker",
        "title": "Here's How Much $1000 Invested In Intuitive Surgical 20 Years Ago Would Be Worth Today",
        "url": "https://www.benzinga.com/insights/news/26/05/52473190/heres-how-much-1000-invested-in-intuitive-surgical-20-years-ago-would-be-worth-today",
        "published_at": "2026-05-11T22:00:26+00:00",
        "type": "other",
        "impact": "low",
        "dedup_group": "isrg_long_term_return_retrospective",
        "tickers_mentioned": [],
        "route_to_synthesis": false
      }
    ]
  },
  "macro_events": []
}