{
  "generated_at": "2026-05-27T00:16:02.110896-04:00",
  "ticker_news": {
    "AAL": [
      {
        "id": "2e24898a93c79ffb",
        "source": "alpaca",
        "publisher": "benzinga",
        "ticker": "AAL",
        "scope": "ticker",
        "title": "American Airlines Says 'Scrolling' Just Got Upgraded As It Chooses Elon Musk's SpaceX As Inflight Wi-Fi Partner On 500 Planes \u2014 AAL Stock Spikes",
        "url": "https://www.benzinga.com/markets/tech/26/05/52798436/american-airlines-says-scrolling-just-got-upgraded-as-it-chooses-elon-musks-spacex-as-inflight-wi-fi-partner-on-500-planes-aal-stock-spikes",
        "published_at": "2026-05-27T03:21:42+00:00",
        "type": "product",
        "impact": "low",
        "dedup_group": "american_airlines_spacex_wifi_partnership",
        "tickers_mentioned": [
          "AAL",
          "TSLA"
        ],
        "route_to_synthesis": false
      }
    ],
    "ALK": [
      {
        "id": "2e24898a93c79ffb",
        "source": "alpaca",
        "publisher": "benzinga",
        "ticker": "ALK",
        "scope": "ticker",
        "title": "American Airlines Says 'Scrolling' Just Got Upgraded As It Chooses Elon Musk's SpaceX As Inflight Wi-Fi Partner On 500 Planes \u2014 AAL Stock Spikes",
        "url": "https://www.benzinga.com/markets/tech/26/05/52798436/american-airlines-says-scrolling-just-got-upgraded-as-it-chooses-elon-musks-spacex-as-inflight-wi-fi-partner-on-500-planes-aal-stock-spikes",
        "published_at": "2026-05-27T03:21:42+00:00",
        "type": "product",
        "impact": "low",
        "dedup_group": "american_airlines_spacex_wifi_partnership",
        "tickers_mentioned": [
          "AAL",
          "TSLA"
        ],
        "route_to_synthesis": false
      }
    ],
    "UAL": [
      {
        "id": "2e24898a93c79ffb",
        "source": "alpaca",
        "publisher": "benzinga",
        "ticker": "UAL",
        "scope": "ticker",
        "title": "American Airlines Says 'Scrolling' Just Got Upgraded As It Chooses Elon Musk's SpaceX As Inflight Wi-Fi Partner On 500 Planes \u2014 AAL Stock Spikes",
        "url": "https://www.benzinga.com/markets/tech/26/05/52798436/american-airlines-says-scrolling-just-got-upgraded-as-it-chooses-elon-musks-spacex-as-inflight-wi-fi-partner-on-500-planes-aal-stock-spikes",
        "published_at": "2026-05-27T03:21:42+00:00",
        "type": "product",
        "impact": "low",
        "dedup_group": "american_airlines_spacex_wifi_partnership",
        "tickers_mentioned": [
          "AAL",
          "TSLA"
        ],
        "route_to_synthesis": false
      }
    ],
    "MU": [
      {
        "id": "f52dc41d71240ef4",
        "source": "alpaca",
        "publisher": "benzinga",
        "ticker": "MU",
        "scope": "ticker",
        "title": "Micron Stock Is 'Too Cheap,' Says Ross Gerber, While Jim Cramer Calls Trillion-Dollar Club Move A 'New Era'",
        "url": "https://www.benzinga.com/markets/tech/26/05/52798237/micron-stock-too-cheap-ross-gerber-jim-cramer-trillion-dollar-club",
        "published_at": "2026-05-27T02:33:48+00:00",
        "type": "analyst",
        "impact": "low",
        "dedup_group": "micron_analyst_commentary_may27",
        "tickers_mentioned": [],
        "route_to_synthesis": false
      },
      {
        "id": "a8388ac0e25a651a",
        "source": "alpaca",
        "publisher": "benzinga",
        "ticker": "MU",
        "scope": "ticker",
        "title": "Micron Technology, Zscaler, Redwire, Intuitive Machines And AMD: Why These 5 Stocks Are On Investors' Radars Today",
        "url": "https://www.benzinga.com/news/26/05/52797985/micron-technology-zscaler-redwire-intuitive-machines-and-amd-why-these-5-stocks-are-on-investors-radars-today",
        "published_at": "2026-05-27T01:21:18+00:00",
        "type": "other",
        "impact": "low",
        "dedup_group": "stocks_on_investors_radars_may27",
        "tickers_mentioned": [
          "ZS",
          "IMAC",
          "AMD"
        ],
        "route_to_synthesis": false
      }
    ],
    "RDW": [
      {
        "id": "a8388ac0e25a651a",
        "source": "alpaca",
        "publisher": "benzinga",
        "ticker": "RDW",
        "scope": "ticker",
        "title": "Micron Technology, Zscaler, Redwire, Intuitive Machines And AMD: Why These 5 Stocks Are On Investors' Radars Today",
        "url": "https://www.benzinga.com/news/26/05/52797985/micron-technology-zscaler-redwire-intuitive-machines-and-amd-why-these-5-stocks-are-on-investors-radars-today",
        "published_at": "2026-05-27T01:21:18+00:00",
        "type": "other",
        "impact": "low",
        "dedup_group": "stocks_on_investors_radars_may27",
        "tickers_mentioned": [
          "ZS",
          "IMAC",
          "AMD"
        ],
        "route_to_synthesis": false
      }
    ]
  },
  "macro_events": []
}