{
  "generated_at": "2026-06-25T15:08:00.287340-04:00",
  "ticker_news": {
    "DELL": [
      {
        "id": "cc99fb02b808be5a",
        "source": "alpaca",
        "publisher": "benzinga",
        "ticker": "DELL",
        "scope": "ticker",
        "title": "Micron Rallies 15%, Apple Sinks 6% On Memory Costs: Stock Market Today",
        "url": "https://www.benzinga.com/markets/equities/26/06/60108692/micron-rallies-apple-sinks-stock-market-thursday",
        "published_at": "2026-06-25T18:14:16+00:00",
        "type": "other",
        "impact": "low",
        "dedup_group": "market_today_recap_micron_apple_memory",
        "tickers_mentioned": [
          "META",
          "AAPL"
        ],
        "route_to_synthesis": false
      }
    ],
    "ESTC": [
      {
        "id": "cc99fb02b808be5a",
        "source": "alpaca",
        "publisher": "benzinga",
        "ticker": "ESTC",
        "scope": "ticker",
        "title": "Micron Rallies 15%, Apple Sinks 6% On Memory Costs: Stock Market Today",
        "url": "https://www.benzinga.com/markets/equities/26/06/60108692/micron-rallies-apple-sinks-stock-market-thursday",
        "published_at": "2026-06-25T18:14:16+00:00",
        "type": "other",
        "impact": "low",
        "dedup_group": "market_today_recap_micron_apple_memory",
        "tickers_mentioned": [
          "META",
          "AAPL"
        ],
        "route_to_synthesis": false
      }
    ],
    "GLW": [
      {
        "id": "cc99fb02b808be5a",
        "source": "alpaca",
        "publisher": "benzinga",
        "ticker": "GLW",
        "scope": "ticker",
        "title": "Micron Rallies 15%, Apple Sinks 6% On Memory Costs: Stock Market Today",
        "url": "https://www.benzinga.com/markets/equities/26/06/60108692/micron-rallies-apple-sinks-stock-market-thursday",
        "published_at": "2026-06-25T18:14:16+00:00",
        "type": "other",
        "impact": "low",
        "dedup_group": "market_today_recap_micron_apple_memory",
        "tickers_mentioned": [
          "META",
          "AAPL"
        ],
        "route_to_synthesis": false
      }
    ],
    "JEF": [
      {
        "id": "cc99fb02b808be5a",
        "source": "alpaca",
        "publisher": "benzinga",
        "ticker": "JEF",
        "scope": "ticker",
        "title": "Micron Rallies 15%, Apple Sinks 6% On Memory Costs: Stock Market Today",
        "url": "https://www.benzinga.com/markets/equities/26/06/60108692/micron-rallies-apple-sinks-stock-market-thursday",
        "published_at": "2026-06-25T18:14:16+00:00",
        "type": "other",
        "impact": "low",
        "dedup_group": "market_today_recap_micron_apple_memory",
        "tickers_mentioned": [
          "META",
          "AAPL"
        ],
        "route_to_synthesis": false
      }
    ],
    "META": [
      {
        "id": "cc99fb02b808be5a",
        "source": "alpaca",
        "publisher": "benzinga",
        "ticker": "META",
        "scope": "ticker",
        "title": "Micron Rallies 15%, Apple Sinks 6% On Memory Costs: Stock Market Today",
        "url": "https://www.benzinga.com/markets/equities/26/06/60108692/micron-rallies-apple-sinks-stock-market-thursday",
        "published_at": "2026-06-25T18:14:16+00:00",
        "type": "other",
        "impact": "low",
        "dedup_group": "market_today_recap_micron_apple_memory",
        "tickers_mentioned": [
          "META",
          "AAPL"
        ],
        "route_to_synthesis": false
      },
      {
        "id": "f19470d83a53ecb0",
        "source": "alpaca",
        "publisher": "benzinga",
        "ticker": "META",
        "scope": "ticker",
        "title": "Why Is DraftKings Stock Falling On Thursday?",
        "url": "https://www.benzinga.com/trading-ideas/movers/26/06/60110872/why-is-draftkings-stock-falling-on-thursday",
        "published_at": "2026-06-25T18:04:45+00:00",
        "type": "other",
        "impact": "low",
        "dedup_group": "draftkings_stock_movement_inquiry",
        "tickers_mentioned": [
          "DKNG"
        ],
        "route_to_synthesis": false
      },
      {
        "id": "354dac5141791650",
        "source": "alpaca",
        "publisher": "benzinga",
        "ticker": "META",
        "scope": "ticker",
        "title": "Kalshi Eyes $40 Billion Valuation, Nearly Doubling Since May As Polymarket Falls Further Behind",
        "url": "https://www.benzinga.com/markets/prediction-markets/26/06/60112160/kalshi-eyes-40-billion-valuation-nearly-doubling-since-may-as-polymarket-falls-further-behind",
        "published_at": "2026-06-25T18:42:05+00:00",
        "type": "rumor",
        "impact": "low",
        "dedup_group": "kalshi_valuation_speculation",
        "tickers_mentioned": [],
        "route_to_synthesis": false
      },
      {
        "id": "5806758ff12865e7",
        "source": "alpaca",
        "publisher": "benzinga",
        "ticker": "META",
        "scope": "ticker",
        "title": "Is AI Talent Acquisition Emerging As A New Investment Signal?",
        "url": "https://www.benzinga.com/Opinion/26/06/60111250/is-ai-talent-acquisition-emerging-as-a-new-investment-signal",
        "published_at": "2026-06-25T18:13:47+00:00",
        "type": "analyst",
        "impact": "low",
        "dedup_group": "ai_talent_acquisition_investment_signal",
        "tickers_mentioned": [],
        "route_to_synthesis": false
      },
      {
        "id": "693f06236b5ea936",
        "source": "alpaca",
        "publisher": "benzinga",
        "ticker": "META",
        "scope": "ticker",
        "title": "8 Communication Services Stocks With Whale Alerts In Today\u2019s Session",
        "url": "https://www.benzinga.com/markets/options/26/06/60109756/8-communication-services-stocks-whale-alerts-today-s-session",
        "published_at": "2026-06-25T17:35:22+00:00",
        "type": "other",
        "impact": "low",
        "dedup_group": "communication_services_whale_alerts_recap",
        "tickers_mentioned": [],
        "route_to_synthesis": false
      }
    ],
    "MSTR": [
      {
        "id": "cc99fb02b808be5a",
        "source": "alpaca",
        "publisher": "benzinga",
        "ticker": "MSTR",
        "scope": "ticker",
        "title": "Micron Rallies 15%, Apple Sinks 6% On Memory Costs: Stock Market Today",
        "url": "https://www.benzinga.com/markets/equities/26/06/60108692/micron-rallies-apple-sinks-stock-market-thursday",
        "published_at": "2026-06-25T18:14:16+00:00",
        "type": "other",
        "impact": "low",
        "dedup_group": "market_today_recap_micron_apple_memory",
        "tickers_mentioned": [
          "META",
          "AAPL"
        ],
        "route_to_synthesis": false
      },
      {
        "id": "1fef28436587743b",
        "source": "alpaca",
        "publisher": "benzinga",
        "ticker": "MSTR",
        "scope": "ticker",
        "title": "MSTR Drops Below $90, Hits 52-Week Low As Sell-Off Accelerates",
        "url": "https://www.benzinga.com/crypto/cryptocurrency/26/06/60112079/mstr-drops-below-90-hits-52-week-low-as-sell-off-accelerates",
        "published_at": "2026-06-25T18:39:59+00:00",
        "type": "other",
        "impact": "medium",
        "dedup_group": "mstr_52week_low_selloff",
        "tickers_mentioned": [],
        "route_to_synthesis": false
      },
      {
        "id": "cfdf5ab90c0bc3c9",
        "source": "alpaca",
        "publisher": "benzinga",
        "ticker": "MSTR",
        "scope": "ticker",
        "title": "Strategy Stock Is Under Pressure: What's Happening?",
        "url": "https://www.benzinga.com/trading-ideas/movers/26/06/60111434/strategy-stock-is-under-pressure-whats-happening",
        "published_at": "2026-06-25T18:18:26+00:00",
        "type": "other",
        "impact": "low",
        "dedup_group": "mstr_pressure_generic",
        "tickers_mentioned": [],
        "route_to_synthesis": false
      },
      {
        "id": "fa1e45df27bdb9f4",
        "source": "alpaca",
        "publisher": "benzinga",
        "ticker": "MSTR",
        "scope": "ticker",
        "title": "10 Information Technology Stocks Whale Activity In Today\u2019s Session",
        "url": "https://www.benzinga.com/markets/options/26/06/60109753/10-information-technology-stocks-whale-activity-today-s-session",
        "published_at": "2026-06-25T17:35:22+00:00",
        "type": "other",
        "impact": "low",
        "dedup_group": "whale_activity_it_stocks_jun25",
        "tickers_mentioned": [],
        "route_to_synthesis": false
      },
      {
        "id": "d712e229024b0739",
        "source": "alpaca",
        "publisher": "benzinga",
        "ticker": "MSTR",
        "scope": "ticker",
        "title": "Bitcoin Loses $60,000: Where Is The Bottom For BTC?",
        "url": "https://www.benzinga.com/crypto/cryptocurrency/26/06/60109319/bitcoin-loses-60000-where-is-the-bottom-for-btc",
        "published_at": "2026-06-25T17:26:38+00:00",
        "type": "macro_commodity",
        "impact": "medium",
        "dedup_group": "btc_60k_support_jun25",
        "tickers_mentioned": [],
        "route_to_synthesis": false
      },
      {
        "id": "e4f2bcc54c7cd4b8",
        "source": "alpaca",
        "publisher": "benzinga",
        "ticker": "MSTR",
        "scope": "ticker",
        "title": "Peter Schiff: MSTR Is In A 'Death Spiral' As Rosen Law Firm Announces Investigation Into Strategy",
        "url": "https://www.benzinga.com/markets/prediction-markets/26/06/60107511/peter-schiff-mstr-is-in-a-death-spiral-as-rosen-law-firm-announces-investigation-into-strategy",
        "published_at": "2026-06-25T16:45:35+00:00",
        "type": "litigation",
        "impact": "high",
        "dedup_group": "mstr_rosen_investigation_death_spiral",
        "tickers_mentioned": [],
        "route_to_synthesis": true
      }
    ],
    "MU": [
      {
        "id": "cc99fb02b808be5a",
        "source": "alpaca",
        "publisher": "benzinga",
        "ticker": "MU",
        "scope": "ticker",
        "title": "Micron Rallies 15%, Apple Sinks 6% On Memory Costs: Stock Market Today",
        "url": "https://www.benzinga.com/markets/equities/26/06/60108692/micron-rallies-apple-sinks-stock-market-thursday",
        "published_at": "2026-06-25T18:14:16+00:00",
        "type": "other",
        "impact": "low",
        "dedup_group": "market_today_recap_micron_apple_memory",
        "tickers_mentioned": [
          "META",
          "AAPL"
        ],
        "route_to_synthesis": false
      },
      {
        "id": "fa1e45df27bdb9f4",
        "source": "alpaca",
        "publisher": "benzinga",
        "ticker": "MU",
        "scope": "ticker",
        "title": "10 Information Technology Stocks Whale Activity In Today\u2019s Session",
        "url": "https://www.benzinga.com/markets/options/26/06/60109753/10-information-technology-stocks-whale-activity-today-s-session",
        "published_at": "2026-06-25T17:35:22+00:00",
        "type": "other",
        "impact": "low",
        "dedup_group": "whale_activity_it_stocks_jun25",
        "tickers_mentioned": [],
        "route_to_synthesis": false
      },
      {
        "id": "79c0a517a221e25c",
        "source": "alpaca",
        "publisher": "benzinga",
        "ticker": "MU",
        "scope": "ticker",
        "title": "Apple Just Confirmed Micron's Biggest AI Prediction",
        "url": "https://www.benzinga.com/trading-ideas/long-ideas/26/06/60108831/apple-just-confirmed-microns-biggest-ai-prediction",
        "published_at": "2026-06-25T17:15:33+00:00",
        "type": "product",
        "impact": "high",
        "dedup_group": "apple_confirms_micron_ai_memory",
        "tickers_mentioned": [
          "AAPL"
        ],
        "route_to_synthesis": true
      },
      {
        "id": "9996c57171b87beb",
        "source": "alpaca",
        "publisher": "benzinga",
        "ticker": "MU",
        "scope": "ticker",
        "title": "Micron Just Delivered 'A Memorable Beat' \u2013 This Analyst Now Sees The Stock At $1,550",
        "url": "https://www.benzinga.com/markets/tech/26/06/60108584/micron-earnings-analyst-reactions-bofa-1550-vivek-arya-susquehanna-2000",
        "published_at": "2026-06-25T17:08:17+00:00",
        "type": "analyst",
        "impact": "high",
        "dedup_group": "micron_analyst_beat_target_1550",
        "tickers_mentioned": [],
        "route_to_synthesis": true
      }
    ],
    "NVDA": [
      {
        "id": "cc99fb02b808be5a",
        "source": "alpaca",
        "publisher": "benzinga",
        "ticker": "NVDA",
        "scope": "ticker",
        "title": "Micron Rallies 15%, Apple Sinks 6% On Memory Costs: Stock Market Today",
        "url": "https://www.benzinga.com/markets/equities/26/06/60108692/micron-rallies-apple-sinks-stock-market-thursday",
        "published_at": "2026-06-25T18:14:16+00:00",
        "type": "other",
        "impact": "low",
        "dedup_group": "market_today_recap_micron_apple_memory",
        "tickers_mentioned": [
          "META",
          "AAPL"
        ],
        "route_to_synthesis": false
      },
      {
        "id": "e5b82880fd86ba48",
        "source": "alpaca",
        "publisher": "benzinga",
        "ticker": "NVDA",
        "scope": "ticker",
        "title": "SpaceX Bond Deal Signals Market 'Bubble,' Allianz Exec Warns: Elon Musk Got '$70 Billion Of Funny Money'",
        "url": "https://www.benzinga.com/markets/prediction-markets/26/06/60107963/spacex-bond-deal-signals-market-bubble-allianz-exec-warns-elon-musk-got-70-billion-of-funny-money",
        "published_at": "2026-06-25T16:54:55+00:00",
        "type": "macro_geopol",
        "impact": "low",
        "dedup_group": "spacex_bond_market_commentary",
        "tickers_mentioned": [],
        "route_to_synthesis": false
      }
    ],
    "QCOM": [
      {
        "id": "cc99fb02b808be5a",
        "source": "alpaca",
        "publisher": "benzinga",
        "ticker": "QCOM",
        "scope": "ticker",
        "title": "Micron Rallies 15%, Apple Sinks 6% On Memory Costs: Stock Market Today",
        "url": "https://www.benzinga.com/markets/equities/26/06/60108692/micron-rallies-apple-sinks-stock-market-thursday",
        "published_at": "2026-06-25T18:14:16+00:00",
        "type": "other",
        "impact": "low",
        "dedup_group": "market_today_recap_micron_apple_memory",
        "tickers_mentioned": [
          "META",
          "AAPL"
        ],
        "route_to_synthesis": false
      }
    ],
    "SNDK": [
      {
        "id": "cc99fb02b808be5a",
        "source": "alpaca",
        "publisher": "benzinga",
        "ticker": "SNDK",
        "scope": "ticker",
        "title": "Micron Rallies 15%, Apple Sinks 6% On Memory Costs: Stock Market Today",
        "url": "https://www.benzinga.com/markets/equities/26/06/60108692/micron-rallies-apple-sinks-stock-market-thursday",
        "published_at": "2026-06-25T18:14:16+00:00",
        "type": "other",
        "impact": "low",
        "dedup_group": "market_today_recap_micron_apple_memory",
        "tickers_mentioned": [
          "META",
          "AAPL"
        ],
        "route_to_synthesis": false
      },
      {
        "id": "fa1e45df27bdb9f4",
        "source": "alpaca",
        "publisher": "benzinga",
        "ticker": "SNDK",
        "scope": "ticker",
        "title": "10 Information Technology Stocks Whale Activity In Today\u2019s Session",
        "url": "https://www.benzinga.com/markets/options/26/06/60109753/10-information-technology-stocks-whale-activity-today-s-session",
        "published_at": "2026-06-25T17:35:22+00:00",
        "type": "other",
        "impact": "low",
        "dedup_group": "whale_activity_it_stocks_jun25",
        "tickers_mentioned": [],
        "route_to_synthesis": false
      },
      {
        "id": "4450dbf5d4a04046",
        "source": "alpaca",
        "publisher": "benzinga",
        "ticker": "SNDK",
        "scope": "ticker",
        "title": "12 Information Technology Stocks Moving In Thursday's Intraday Session",
        "url": "https://www.benzinga.com/trading-ideas/movers/26/06/60108445/12-information-technology-stocks-moving-thursday-s-intraday-session",
        "published_at": "2026-06-25T17:05:48+00:00",
        "type": "other",
        "impact": "low",
        "dedup_group": "intraday_movers_generic",
        "tickers_mentioned": [],
        "route_to_synthesis": false
      }
    ],
    "TECH": [
      {
        "id": "cc99fb02b808be5a",
        "source": "alpaca",
        "publisher": "benzinga",
        "ticker": "TECH",
        "scope": "ticker",
        "title": "Micron Rallies 15%, Apple Sinks 6% On Memory Costs: Stock Market Today",
        "url": "https://www.benzinga.com/markets/equities/26/06/60108692/micron-rallies-apple-sinks-stock-market-thursday",
        "published_at": "2026-06-25T18:14:16+00:00",
        "type": "other",
        "impact": "low",
        "dedup_group": "market_today_recap_micron_apple_memory",
        "tickers_mentioned": [
          "META",
          "AAPL"
        ],
        "route_to_synthesis": false
      },
      {
        "id": "4d5485e1a981b7b1",
        "source": "alpaca",
        "publisher": "benzinga",
        "ticker": "TECH",
        "scope": "ticker",
        "title": "12 Health Care Stocks Moving In Thursday's Intraday Session",
        "url": "https://www.benzinga.com/trading-ideas/movers/26/06/60108447/12-health-care-stocks-moving-thursday-s-intraday-session",
        "published_at": "2026-06-25T17:05:49+00:00",
        "type": "other",
        "impact": "low",
        "dedup_group": "intraday_movers_healthcare_generic",
        "tickers_mentioned": [],
        "route_to_synthesis": false
      }
    ],
    "COIN": [
      {
        "id": "39289c274a08364b",
        "source": "alpaca",
        "publisher": "benzinga",
        "ticker": "COIN",
        "scope": "ticker",
        "title": "Bitcoin Plunges Below $60,000 For The Second Straight Day: What Is Going On?",
        "url": "https://www.benzinga.com/crypto/cryptocurrency/26/06/60104605/bitcoin-plunges-below-60000-for-the-second-straight-day-what-is-going-on",
        "published_at": "2026-06-25T15:40:24+00:00",
        "type": "macro_commodity",
        "impact": "medium",
        "dedup_group": "btc_60k_support_jun25",
        "tickers_mentioned": [],
        "route_to_synthesis": false
      }
    ],
    "DECK": [
      {
        "id": "fdb5ee4b32c0e9b3",
        "source": "alpaca",
        "publisher": "benzinga",
        "ticker": "DECK",
        "scope": "ticker",
        "title": "'Big Short' Star Steve Eisman Warns Middle Class Is 'Starting To Crack', Tax Refunds 'Went Into The Gas Tank'",
        "url": "https://www.benzinga.com/markets/prediction-markets/26/06/60101657/big-short-star-steve-eisman-warns-middle-class-is-starting-to-crack-tax-refunds-went-into-the-gas-tank",
        "published_at": "2026-06-25T14:43:36+00:00",
        "type": "macro_econ",
        "impact": "low",
        "dedup_group": "eisman_consumer_weakness_commentary",
        "tickers_mentioned": [],
        "route_to_synthesis": false
      }
    ],
    "KHC": [
      {
        "id": "fdb5ee4b32c0e9b3",
        "source": "alpaca",
        "publisher": "benzinga",
        "ticker": "KHC",
        "scope": "ticker",
        "title": "'Big Short' Star Steve Eisman Warns Middle Class Is 'Starting To Crack', Tax Refunds 'Went Into The Gas Tank'",
        "url": "https://www.benzinga.com/markets/prediction-markets/26/06/60101657/big-short-star-steve-eisman-warns-middle-class-is-starting-to-crack-tax-refunds-went-into-the-gas-tank",
        "published_at": "2026-06-25T14:43:36+00:00",
        "type": "macro_econ",
        "impact": "low",
        "dedup_group": "eisman_consumer_weakness_commentary",
        "tickers_mentioned": [],
        "route_to_synthesis": false
      }
    ],
    "NKE": [
      {
        "id": "fdb5ee4b32c0e9b3",
        "source": "alpaca",
        "publisher": "benzinga",
        "ticker": "NKE",
        "scope": "ticker",
        "title": "'Big Short' Star Steve Eisman Warns Middle Class Is 'Starting To Crack', Tax Refunds 'Went Into The Gas Tank'",
        "url": "https://www.benzinga.com/markets/prediction-markets/26/06/60101657/big-short-star-steve-eisman-warns-middle-class-is-starting-to-crack-tax-refunds-went-into-the-gas-tank",
        "published_at": "2026-06-25T14:43:36+00:00",
        "type": "macro_econ",
        "impact": "low",
        "dedup_group": "eisman_consumer_weakness_commentary",
        "tickers_mentioned": [],
        "route_to_synthesis": false
      }
    ],
    "LLY": [
      {
        "id": "ffeb5d4145015bd2",
        "source": "alpaca",
        "publisher": "benzinga",
        "ticker": "LLY",
        "scope": "ticker",
        "title": "Small-Cap ProQR Therapeutics Secures Funding From Eli Lilly On Early Trial Success",
        "url": "https://www.benzinga.com/trading-ideas/movers/26/06/60098410/small-cap-proqr-therapeutics-secures-funding-from-eli-lilly-on-early-trial-success",
        "published_at": "2026-06-25T13:56:34+00:00",
        "type": "product",
        "impact": "medium",
        "dedup_group": "proqr_eli_lilly_funding",
        "tickers_mentioned": [
          "PQRR"
        ],
        "route_to_synthesis": true
      }
    ],
    "DKNG": [
      {
        "id": "f19470d83a53ecb0",
        "source": "alpaca",
        "publisher": "benzinga",
        "ticker": "DKNG",
        "scope": "ticker",
        "title": "Why Is DraftKings Stock Falling On Thursday?",
        "url": "https://www.benzinga.com/trading-ideas/movers/26/06/60110872/why-is-draftkings-stock-falling-on-thursday",
        "published_at": "2026-06-25T18:04:45+00:00",
        "type": "other",
        "impact": "low",
        "dedup_group": "draftkings_stock_movement_inquiry",
        "tickers_mentioned": [
          "DKNG"
        ],
        "route_to_synthesis": false
      }
    ],
    "KDP": [
      {
        "id": "28fa65dd46b1eee5",
        "source": "alpaca",
        "publisher": "benzinga",
        "ticker": "KDP",
        "scope": "ticker",
        "title": "This Keurig Dr Pepper Analyst Turns Bullish; Here Are Top 4 Upgrades For Thursday",
        "url": "https://www.benzinga.com/analyst-stock-ratings/upgrades/26/06/60106453/this-keurig-dr-pepper-analyst-turns-bullish-here-are-top-4-upgrades-for-thursday",
        "published_at": "2026-06-25T16:21:15+00:00",
        "type": "analyst",
        "impact": "medium",
        "dedup_group": "kdp_analyst_upgrade_jun25",
        "tickers_mentioned": [],
        "route_to_synthesis": false
      }
    ],
    "GOOG": [
      {
        "id": "bb189c8777e72034",
        "source": "alpaca",
        "publisher": "benzinga",
        "ticker": "GOOG",
        "scope": "ticker",
        "title": "Google Finance Exits Beta, Launches Portfolios, AI Tools, New Dedicated Android App",
        "url": "https://www.benzinga.com/markets/tech/26/06/60105565/google-finance-exits-beta-launches-portfolios-ai-tools-new-dedicated-android-app",
        "published_at": "2026-06-25T16:02:35+00:00",
        "type": "product",
        "impact": "medium",
        "dedup_group": "google_finance_launch_portfolios_ai",
        "tickers_mentioned": [],
        "route_to_synthesis": true
      },
      {
        "id": "9624ebdf61e20bcf",
        "source": "alpaca",
        "publisher": "benzinga",
        "ticker": "GOOG",
        "scope": "ticker",
        "title": "Alphabet Stock Is Trading Lower Thursday: What's Driving The Action?",
        "url": "https://www.benzinga.com/trading-ideas/movers/26/06/60100757/alphabet-stock-is-trading-lower-thursday-whats-driving-the-action",
        "published_at": "2026-06-25T14:28:40+00:00",
        "type": "other",
        "impact": "low",
        "dedup_group": "alphabet_stock_movement_inquiry",
        "tickers_mentioned": [],
        "route_to_synthesis": false
      }
    ],
    "IBM": [
      {
        "id": "3905dc9cab93b86b",
        "source": "alpaca",
        "publisher": "benzinga",
        "ticker": "IBM",
        "scope": "ticker",
        "title": "IBM Unveils Record-Breaking Chip Technology",
        "url": "https://www.benzinga.com/markets/tech/26/06/60099234/ibm-unveils-record-breaking-chip-technology",
        "published_at": "2026-06-25T14:06:47+00:00",
        "type": "product",
        "impact": "medium",
        "dedup_group": "ibm_record_chip_technology",
        "tickers_mentioned": [],
        "route_to_synthesis": true
      }
    ],
    "WDC": [
      {
        "id": "b4387c4fa808d59c",
        "source": "alpaca",
        "publisher": "benzinga",
        "ticker": "WDC",
        "scope": "ticker",
        "title": "Why Is Seagate Technology Stock Surging On Thursday?",
        "url": "https://www.benzinga.com/trading-ideas/movers/26/06/60107652/why-is-seagate-technology-stock-surging-on-thursday",
        "published_at": "2026-06-25T16:48:25+00:00",
        "type": "other",
        "impact": "low",
        "dedup_group": "seagate_stock_surging_jun25",
        "tickers_mentioned": [],
        "route_to_synthesis": false
      }
    ],
    "LYV": [
      {
        "id": "693f06236b5ea936",
        "source": "alpaca",
        "publisher": "benzinga",
        "ticker": "LYV",
        "scope": "ticker",
        "title": "8 Communication Services Stocks With Whale Alerts In Today\u2019s Session",
        "url": "https://www.benzinga.com/markets/options/26/06/60109756/8-communication-services-stocks-whale-alerts-today-s-session",
        "published_at": "2026-06-25T17:35:22+00:00",
        "type": "other",
        "impact": "low",
        "dedup_group": "communication_services_whale_alerts_recap",
        "tickers_mentioned": [],
        "route_to_synthesis": false
      }
    ],
    "PLTR": [
      {
        "id": "fa1e45df27bdb9f4",
        "source": "alpaca",
        "publisher": "benzinga",
        "ticker": "PLTR",
        "scope": "ticker",
        "title": "10 Information Technology Stocks Whale Activity In Today\u2019s Session",
        "url": "https://www.benzinga.com/markets/options/26/06/60109753/10-information-technology-stocks-whale-activity-today-s-session",
        "published_at": "2026-06-25T17:35:22+00:00",
        "type": "other",
        "impact": "low",
        "dedup_group": "whale_activity_it_stocks_jun25",
        "tickers_mentioned": [],
        "route_to_synthesis": false
      }
    ],
    "NRIX": [
      {
        "id": "4d5485e1a981b7b1",
        "source": "alpaca",
        "publisher": "benzinga",
        "ticker": "NRIX",
        "scope": "ticker",
        "title": "12 Health Care Stocks Moving In Thursday's Intraday Session",
        "url": "https://www.benzinga.com/trading-ideas/movers/26/06/60108447/12-health-care-stocks-moving-thursday-s-intraday-session",
        "published_at": "2026-06-25T17:05:49+00:00",
        "type": "other",
        "impact": "low",
        "dedup_group": "intraday_movers_healthcare_generic",
        "tickers_mentioned": [],
        "route_to_synthesis": false
      }
    ],
    "SLS": [
      {
        "id": "4d5485e1a981b7b1",
        "source": "alpaca",
        "publisher": "benzinga",
        "ticker": "SLS",
        "scope": "ticker",
        "title": "12 Health Care Stocks Moving In Thursday's Intraday Session",
        "url": "https://www.benzinga.com/trading-ideas/movers/26/06/60108447/12-health-care-stocks-moving-thursday-s-intraday-session",
        "published_at": "2026-06-25T17:05:49+00:00",
        "type": "other",
        "impact": "low",
        "dedup_group": "intraday_movers_healthcare_generic",
        "tickers_mentioned": [],
        "route_to_synthesis": false
      },
      {
        "id": "e1f7426477b0efeb",
        "source": "alpaca",
        "publisher": "benzinga",
        "ticker": "SLS",
        "scope": "ticker",
        "title": "Why SELLAS Life Sciences Stock Is Surging Thursday",
        "url": "https://www.benzinga.com/trading-ideas/movers/26/06/60110972/why-sellas-life-sciences-stock-is-surging-thursday",
        "published_at": "2026-06-25T18:07:40+00:00",
        "type": "other",
        "impact": "medium",
        "dedup_group": "sls_surge_thursday",
        "tickers_mentioned": [],
        "route_to_synthesis": false
      }
    ],
    "RDW": [
      {
        "id": "cc890a06fb26d596",
        "source": "alpaca",
        "publisher": "benzinga",
        "ticker": "RDW",
        "scope": "ticker",
        "title": "Why Is Redwire Stock Falling On Thursday?",
        "url": "https://www.benzinga.com/trading-ideas/movers/26/06/60110753/why-is-redwire-stock-falling-on-thursday",
        "published_at": "2026-06-25T18:01:04+00:00",
        "type": "other",
        "impact": "low",
        "dedup_group": "rdw_stock_falling_jun25",
        "tickers_mentioned": [],
        "route_to_synthesis": false
      }
    ],
    "MRK": [
      {
        "id": "12632ea6cc481399",
        "source": "alpaca",
        "publisher": "benzinga",
        "ticker": "MRK",
        "scope": "ticker",
        "title": "Gilead's Trodelvy Expands Reach With New FDA Approval In Breast Cancer",
        "url": "https://www.benzinga.com/news/fda/26/06/60103508/gileads-trodelvy-expands-reach-with-new-fda-approval-in-breast-cancer",
        "published_at": "2026-06-25T15:17:29+00:00",
        "type": "product",
        "impact": "medium",
        "dedup_group": "gilead_trodelvy_fda_breast_cancer",
        "tickers_mentioned": [
          "GILD"
        ],
        "route_to_synthesis": false
      }
    ],
    "SERV": [
      {
        "id": "51df6b7a0768c964",
        "source": "alpaca",
        "publisher": "benzinga",
        "ticker": "SERV",
        "scope": "ticker",
        "title": "10 Consumer Discretionary Stocks Whale Activity In Today\u2019s Session",
        "url": "https://www.benzinga.com/markets/options/26/06/60109754/10-consumer-discretionary-stocks-whale-activity-today-s-session",
        "published_at": "2026-06-25T17:35:22+00:00",
        "type": "other",
        "impact": "low",
        "dedup_group": "whale_activity_consumer_discretionary_jun25",
        "tickers_mentioned": [],
        "route_to_synthesis": false
      }
    ]
  },
  "macro_events": []
}