{
  "generated_at": "2026-05-28T18:01:35.019337-04:00",
  "window_days": 30,
  "total_alerts": 1957,
  "per_type": {
    "watchlist": {
      "count": 561,
      "horizons": {
        "1d": {
          "evaluated": 556,
          "hit_rate": 0.514,
          "avg_return_pct": -0.73
        },
        "3d": {
          "evaluated": 527,
          "hit_rate": 0.613,
          "avg_return_pct": 0.72
        },
        "5d": {
          "evaluated": 515,
          "hit_rate": 0.563,
          "avg_return_pct": 0.56
        }
      }
    },
    "big_move": {
      "count": 1136,
      "horizons": {
        "1d": {
          "evaluated": 1107,
          "hit_rate": 0.425,
          "avg_return_pct": 0.19
        },
        "3d": {
          "evaluated": 1058,
          "hit_rate": 0.458,
          "avg_return_pct": 0.08
        },
        "5d": {
          "evaluated": 1028,
          "hit_rate": 0.466,
          "avg_return_pct": -0.07
        }
      }
    },
    "catalyst": {
      "count": 108,
      "horizons": {
        "1d": {
          "evaluated": 100,
          "hit_rate": 0.53,
          "avg_return_pct": 1.49
        },
        "3d": {
          "evaluated": 95,
          "hit_rate": 0.558,
          "avg_return_pct": 1.65
        },
        "5d": {
          "evaluated": 95,
          "hit_rate": 0.621,
          "avg_return_pct": 1.66
        }
      }
    },
    "delta_new_top20": {
      "count": 152,
      "horizons": {
        "1d": {
          "evaluated": 151,
          "hit_rate": 0.483,
          "avg_return_pct": 0.64
        },
        "3d": {
          "evaluated": 145,
          "hit_rate": 0.476,
          "avg_return_pct": 1.08
        },
        "5d": {
          "evaluated": 145,
          "hit_rate": 0.455,
          "avg_return_pct": 0.55
        }
      }
    }
  }
}