{
  "generated_at": "2026-06-10T14:39:00.230146-04:00",
  "window_days": 30,
  "slippage_round_trip_pct": 0.5,
  "total_alerts": 1720,
  "per_type": {
    "watchlist": {
      "count": 519,
      "direction_basis": "move",
      "horizons": {
        "1d": {
          "evaluated": 487,
          "hit_rate": 0.478,
          "avg_return_pct": -0.62,
          "hit_rate_net": 0.37,
          "avg_return_net_pct": -1.12
        },
        "3d": {
          "evaluated": 426,
          "hit_rate": 0.538,
          "avg_return_pct": -0.34,
          "hit_rate_net": 0.491,
          "avg_return_net_pct": -0.84
        },
        "5d": {
          "evaluated": 412,
          "hit_rate": 0.522,
          "avg_return_pct": -0.8,
          "hit_rate_net": 0.502,
          "avg_return_net_pct": -1.3
        }
      }
    },
    "big_move": {
      "count": 667,
      "direction_basis": "move",
      "horizons": {
        "1d": {
          "evaluated": 659,
          "hit_rate": 0.451,
          "avg_return_pct": -0.17,
          "hit_rate_net": 0.364,
          "avg_return_net_pct": -0.67
        },
        "3d": {
          "evaluated": 632,
          "hit_rate": 0.421,
          "avg_return_pct": 0.22,
          "hit_rate_net": 0.402,
          "avg_return_net_pct": -0.28
        },
        "5d": {
          "evaluated": 624,
          "hit_rate": 0.495,
          "avg_return_pct": 1.44,
          "hit_rate_net": 0.473,
          "avg_return_net_pct": 0.94
        }
      }
    },
    "delta_new_top20": {
      "count": 232,
      "direction_basis": "move",
      "horizons": {
        "1d": {
          "evaluated": 214,
          "hit_rate": 0.481,
          "avg_return_pct": -0.53,
          "hit_rate_net": 0.453,
          "avg_return_net_pct": -1.02
        },
        "3d": {
          "evaluated": 186,
          "hit_rate": 0.425,
          "avg_return_pct": -1.2,
          "hit_rate_net": 0.409,
          "avg_return_net_pct": -1.7
        },
        "5d": {
          "evaluated": 184,
          "hit_rate": 0.44,
          "avg_return_pct": -1.66,
          "hit_rate_net": 0.429,
          "avg_return_net_pct": -2.16
        }
      }
    },
    "catalyst": {
      "count": 77,
      "direction_basis": "move",
      "horizons": {
        "1d": {
          "evaluated": 74,
          "hit_rate": 0.595,
          "avg_return_pct": 3.0,
          "hit_rate_net": 0.581,
          "avg_return_net_pct": 2.5
        },
        "3d": {
          "evaluated": 68,
          "hit_rate": 0.559,
          "avg_return_pct": 2.92,
          "hit_rate_net": 0.559,
          "avg_return_net_pct": 2.42
        },
        "5d": {
          "evaluated": 68,
          "hit_rate": 0.574,
          "avg_return_pct": 1.32,
          "hit_rate_net": 0.544,
          "avg_return_net_pct": 0.82
        }
      }
    },
    "serenity_match": {
      "count": 219,
      "direction_basis": "move",
      "horizons": {
        "1d": {
          "evaluated": 137,
          "hit_rate": 0.27,
          "avg_return_pct": -3.29,
          "hit_rate_net": 0.226,
          "avg_return_net_pct": -3.79
        },
        "3d": {
          "evaluated": 12,
          "hit_rate": 0.167,
          "avg_return_pct": -4.35,
          "hit_rate_net": 0.083,
          "avg_return_net_pct": -4.85
        },
        "5d": {
          "evaluated": 4,
          "hit_rate": 1.0,
          "avg_return_pct": 3.89,
          "hit_rate_net": 1.0,
          "avg_return_net_pct": 3.39
        }
      }
    },
    "ripple": {
      "count": 5,
      "direction_basis": "move",
      "horizons": {
        "1d": {
          "evaluated": 2,
          "hit_rate": 0.5,
          "avg_return_pct": 0.38,
          "hit_rate_net": 0.5,
          "avg_return_net_pct": -0.12
        },
        "3d": {
          "evaluated": 0,
          "hit_rate": null,
          "avg_return_pct": null,
          "hit_rate_net": null,
          "avg_return_net_pct": null
        },
        "5d": {
          "evaluated": 0,
          "hit_rate": null,
          "avg_return_pct": null,
          "hit_rate_net": null,
          "avg_return_net_pct": null
        }
      }
    },
    "delta_accel": {
      "count": 1,
      "direction_basis": "move",
      "horizons": {
        "1d": {
          "evaluated": 0,
          "hit_rate": null,
          "avg_return_pct": null,
          "hit_rate_net": null,
          "avg_return_net_pct": null
        },
        "3d": {
          "evaluated": 0,
          "hit_rate": null,
          "avg_return_pct": null,
          "hit_rate_net": null,
          "avg_return_net_pct": null
        },
        "5d": {
          "evaluated": 0,
          "hit_rate": null,
          "avg_return_pct": null,
          "hit_rate_net": null,
          "avg_return_net_pct": null
        }
      }
    }
  }
}